{
    "CP_Model": {
        "Times: ": [
            0,
            0.65,
            0.68,
            0.68,
            0.7,
            0.71,
            0.73,
            0.75,
            0.75,
            0.76,
            0.77,
            0.79,
            0.82,
            0.84,
            0.85,
            0.86,
            0.91,
            0.93,
            0.99,
            1.09,
            1.1,
            1.13,
            1.15,
            1.27,
            1.33,
            1.34,
            1.36,
            1.37,
            1.38,
            1.39,
            1.41,
            1.42,
            1.47,
            1.56,
            1.73,
            1.74,
            1.75,
            1.83,
            1.84,
            1.86,
            1.93,
            1.96,
            2.07,
            2.21,
            2.37,
            2.48,
            2.52,
            2.6,
            2.7,
            2.86,
            2.87,
            3.18,
            3.23,
            3.24,
            3.47,
            4.03,
            4.24,
            5.18,
            5.18,
            5.32,
            5.41,
            5.62,
            5.64,
            5.76,
            6.22,
            6.5,
            6.54,
            6.8,
            6.83,
            6.83,
            10.68,
            11.02,
            52.59,
            52.6,
            52.6,
            52.69,
            54.5,
            55.54,
            55.72,
            55.83,
            56.21,
            56.31,
            56.37,
            56.85,
            56.9,
            57.15,
            57.23,
            57.32,
            57.33,
            57.33,
            57.74,
            58.25,
            58.37,
            58.47,
            58.66,
            63.85,
            63.87,
            64.02,
            65.85,
            65.87,
            65.95,
            65.95,
            66.14,
            66.29,
            66.38,
            66.67,
            67.19,
            67.26,
            67.49,
            68.13,
            68.6,
            600
        ],
        "Solution Costs: ": [
            null,
            640.8,
            620.4,
            547.6,
            531.7,
            514.9,
            511.1,
            480.6,
            462.9,
            441.5,
            438.0,
            436.0,
            435.4,
            417.9,
            410.4,
            409.6,
            404.8,
            393.8,
            382.8,
            381.2,
            380.2,
            378.9,
            358.7,
            353.0,
            351.8,
            351.8,
            343.9,
            341.1,
            338.9,
            334.9,
            334.7,
            327.2,
            324.8,
            316.6,
            311.8,
            309.2,
            309.2,
            305.7,
            303.0,
            301.0,
            300.3,
            298.5,
            294.1,
            293.4,
            292.0,
            288.8,
            285.2,
            284.1,
            283.2,
            283.2,
            283.1,
            283.1,
            278.4,
            278.1,
            277.7,
            276.6,
            275.9,
            275.9,
            275.6,
            275.3,
            272.8,
            271.8,
            271.3,
            271.2,
            271.1,
            270.7,
            269.4,
            268.9,
            266.0,
            265.9,
            265.7,
            265.4,
            264.2,
            262.8,
            262.6,
            262.3,
            262.3,
            261.7,
            260.1,
            259.3,
            258.5,
            257.5,
            256.6,
            256.3,
            255.7,
            255.2,
            254.0,
            252.5,
            252.3,
            252.1,
            251.7,
            250.9,
            250.8,
            250.6,
            250.0,
            249.7,
            249.5,
            249.3,
            248.3,
            246.4,
            245.6,
            243.6,
            243.3,
            242.5,
            240.2,
            239.7,
            239.3,
            238.5,
            237.7,
            237.1,
            236.4
        ],
        "Optimality: ": false,
        "Best Cost: ": 236.4,
        "Best Path: ": [
            [
                23,
                1,
                19,
                37,
                18,
                22
            ],
            [
                45,
                27,
                15,
                46,
                21,
                2,
                14
            ],
            [
                36,
                20,
                33,
                10
            ],
            [
                26,
                11,
                42,
                4,
                13,
                29,
                16,
                47
            ],
            [
                12,
                5,
                31,
                43,
                39,
                8
            ],
            [
                28,
                7,
                3,
                25,
                38,
                6
            ],
            [
                44,
                35,
                32,
                40,
                34,
                9,
                24,
                30,
                41,
                17
            ]
        ]
    },
    "DIDP_Complete": {
        "Times: ": [
            0,
            0.0055085,
            0.029468,
            0.0682055,
            0.1517297,
            0.1753085,
            0.1846928,
            0.6009428,
            0.6034988,
            2.1379996,
            2.1609519,
            2.1819121,
            2.318215,
            2.3189361,
            2.3776566,
            3.4726368,
            4.0909831,
            4.1610352,
            4.2614608,
            4.9565722,
            7.4283976,
            7.5860429,
            7.5901979,
            7.5940216,
            7.5946597,
            9.195771,
            9.2392297,
            11.7468067,
            600.0502253,
            600
        ],
        "Solution Costs: ": [
            null,
            293.1,
            277.9,
            265.1,
            262.1,
            256.4,
            252.3,
            250.1,
            242.0,
            239.5,
            238.1,
            236.5,
            235.8,
            235.2,
            235.0,
            234.6,
            234.6,
            233.5,
            232.4,
            227.0,
            226.8,
            226.2,
            224.5,
            220.4,
            218.2,
            216.5,
            215.4,
            211.9,
            211.9
        ],
        "Optimality: ": false,
        "Best Cost: ": 211.9,
        "Best Path: ": [
            [
                26,
                20,
                39,
                8,
                15,
                27
            ],
            [
                11,
                42,
                4,
                24,
                9,
                34,
                17,
                14
            ],
            [
                13,
                46,
                30,
                21,
                29,
                33
            ],
            [
                3,
                25,
                19,
                37,
                38,
                22,
                18
            ],
            [
                2,
                10,
                28,
                45,
                7,
                36,
                44
            ],
            [
                1,
                6,
                5,
                47,
                41
            ],
            [
                40,
                16,
                32,
                12,
                31,
                43,
                23,
                35
            ]
        ]
    },
    "DIDP_No_Bound": {
        "Times: ": [
            0,
            0.0048722,
            0.0215923,
            0.0222492,
            0.0533879,
            0.2518985,
            0.3304238,
            0.6736965,
            0.9149259,
            1.6490685,
            4.2603946,
            8.401353,
            41.9402985,
            41.9414735,
            41.9428632,
            42.0130807,
            42.0144963,
            42.0477586,
            53.8736576,
            600.0319654,
            600
        ],
        "Solution Costs: ": [
            null,
            269.1,
            257.9,
            231.1,
            228.9,
            227.4,
            227.2,
            226.7,
            225.7,
            223.4,
            222.5,
            222.3,
            222.1,
            220.9,
            220.2,
            217.1,
            216.4,
            210.1,
            210.0,
            210.0
        ],
        "Optimality: ": false,
        "Best Cost: ": 210.0,
        "Best Path: ": [
            [
                18,
                45,
                34,
                9,
                24,
                4,
                11,
                42
            ],
            [
                17,
                47,
                16,
                28,
                29,
                46,
                2
            ],
            [
                14,
                41,
                10,
                33,
                21,
                30,
                13
            ],
            [
                44,
                38,
                19,
                37,
                3,
                39,
                8
            ],
            [
                23,
                12,
                40,
                7,
                1
            ],
            [
                43,
                31,
                5,
                22,
                6,
                25
            ],
            [
                35,
                32,
                36,
                27,
                15,
                26,
                20
            ]
        ]
    },
    "DIDP_No_Implied": {
        "Times: ": [
            0,
            0.0054815,
            0.0468416,
            0.109528,
            0.2058031,
            0.2107467,
            0.221151,
            0.2215563,
            1.0631745,
            1.0639184,
            7.0565996,
            7.058511,
            7.0609008,
            7.0612957,
            7.0618674,
            7.0647105,
            7.0766045,
            7.0811169,
            7.216861,
            7.3724665,
            600.022788,
            600
        ],
        "Solution Costs: ": [
            null,
            293.1,
            277.9,
            269.6,
            266.7,
            261.8,
            260.9,
            258.7,
            254.3,
            252.4,
            249.3,
            249.0,
            248.1,
            245.5,
            240.3,
            239.6,
            234.8,
            233.5,
            233.2,
            222.0,
            222.0
        ],
        "Optimality: ": false,
        "Best Cost: ": 222.0,
        "Best Path: ": [
            [
                11,
                20,
                26,
                39,
                8
            ],
            [
                46,
                42,
                15,
                40,
                35,
                18
            ],
            [
                13,
                4,
                24,
                30,
                21,
                29,
                33,
                14
            ],
            [
                3,
                25,
                19,
                37,
                38,
                43,
                23
            ],
            [
                2,
                10,
                28,
                45,
                7,
                36,
                44
            ],
            [
                9,
                27,
                34,
                47,
                16,
                17,
                41
            ],
            [
                22,
                1,
                6,
                5,
                12,
                31,
                32
            ]
        ]
    },
    "DIDP_Base": {
        "Times: ": [
            0,
            0.0051626,
            0.0267252,
            0.0270476,
            0.0355712,
            0.0386003,
            0.0477274,
            0.1128481,
            0.1726704,
            0.2418511,
            0.2524518,
            0.8968872,
            0.9229158,
            0.9562307,
            0.9659335,
            1.5411834,
            2.2497245,
            5.5679172,
            5.5837864,
            6.8265795,
            6.8364401,
            6.9955680000000005,
            7.1618992,
            7.1665656,
            7.2535772,
            84.659581,
            84.66023,
            84.6707613,
            578.0356915,
            578.064243,
            578.0648018,
            579.7451505,
            579.7524745,
            600.002657,
            600
        ],
        "Solution Costs: ": [
            null,
            269.1,
            246.9,
            234.5,
            234.1,
            234.0,
            231.1,
            230.4,
            228.5,
            227.2,
            226.8,
            225.5,
            225.4,
            225.4,
            225.4,
            223.4,
            222.5,
            222.0,
            220.2,
            218.3,
            216.4,
            216.3,
            214.9,
            214.8,
            214.3,
            212.8,
            211.2,
            210.5,
            210.1,
            209.0,
            208.7,
            208.5,
            208.4,
            208.4
        ],
        "Optimality: ": false,
        "Best Cost: ": 208.4,
        "Best Path: ": [
            [
                18,
                40,
                34,
                9,
                24,
                4,
                11,
                42
            ],
            [
                17,
                16,
                47,
                29,
                30,
                13,
                46
            ],
            [
                14,
                41,
                2,
                10,
                33,
                21
            ],
            [
                44,
                32,
                19,
                37,
                3,
                39,
                8
            ],
            [
                23,
                31,
                12,
                5,
                7,
                45,
                28
            ],
            [
                43,
                1,
                6,
                38,
                22,
                25
            ],
            [
                35,
                36,
                27,
                15,
                26,
                20
            ]
        ]
    },
    "DIDP_No_Implied_Opt": {
        "Times: ": [
            0,
            0.0111441,
            0.2018427,
            0.2119498,
            0.3182253,
            0.7292686,
            5.519035,
            5.5547373,
            5.5637385,
            12.0373938,
            12.0609004,
            12.0732673,
            12.074833,
            12.0749974,
            13.5534064,
            13.5663207,
            13.5676175,
            13.5678953,
            13.5681428,
            599.9972211,
            600
        ],
        "Solution Costs: ": [
            null,
            293.1,
            277.9,
            267.8,
            265.1,
            262.1,
            252.0,
            251.8,
            248.4,
            241.7,
            241.3,
            234.0,
            233.9,
            232.7,
            232.3,
            230.7,
            230.7,
            227.8,
            222.0,
            222.0
        ],
        "Optimality: ": false,
        "Best Cost: ": 222.0,
        "Best Path: ": [
            [
                11,
                20,
                26,
                39,
                8
            ],
            [
                46,
                13,
                42,
                15,
                27,
                40,
                18
            ],
            [
                4,
                24,
                30,
                21,
                16,
                41
            ],
            [
                29,
                2,
                10,
                28,
                47,
                17,
                14
            ],
            [
                25,
                37,
                22,
                6,
                31,
                43,
                23
            ],
            [
                3,
                19,
                38,
                1,
                5,
                12
            ],
            [
                33,
                9,
                34,
                45,
                7,
                36,
                32,
                44,
                35
            ]
        ]
    },
    "DIDP_Base_Opt": {
        "Times: ": [
            0,
            0.0042401,
            0.0209487,
            0.0214634,
            0.0229295,
            0.0255811,
            0.0366024,
            0.1156135,
            1.0141854,
            1.0152869,
            1.3549103,
            1.3588647,
            1.4358431,
            1.4539081999999999,
            1.9789762,
            1.9886179,
            2.1107152,
            233.9339846,
            600.1007845,
            600
        ],
        "Solution Costs: ": [
            null,
            269.1,
            246.9,
            243.0,
            242.2,
            236.4,
            231.1,
            230.1,
            222.4,
            220.6,
            220.2,
            218.6,
            216.4,
            214.4,
            213.9,
            212.9,
            208.6,
            205.8,
            205.8
        ],
        "Optimality: ": false,
        "Best Cost: ": 205.8,
        "Best Path: ": [
            [
                14,
                16,
                47,
                28,
                29,
                13,
                46
            ],
            [
                40,
                7,
                45,
                8,
                39,
                26,
                20
            ],
            [
                34,
                9,
                24,
                4,
                11,
                42,
                15,
                27
            ],
            [
                41,
                2,
                10,
                33,
                30,
                21
            ],
            [
                44,
                35,
                32,
                38,
                19,
                25,
                37,
                3
            ],
            [
                17,
                23,
                31,
                12,
                5,
                36
            ],
            [
                18,
                43,
                1,
                6,
                22
            ]
        ]
    },
    "CP_Model_No_Imp": {
        "Times: ": [
            0,
            0.74,
            0.77,
            0.78,
            0.8,
            0.82,
            0.85,
            0.85,
            0.86,
            0.88,
            0.91,
            0.93,
            0.94,
            0.96,
            1.01,
            1.05,
            1.08,
            1.1,
            1.11,
            1.12,
            1.16,
            1.19,
            1.26,
            1.34,
            1.42,
            1.43,
            1.47,
            1.47,
            1.48,
            1.56,
            1.74,
            1.86,
            1.87,
            1.9,
            1.92,
            1.97,
            2.04,
            2.11,
            2.8,
            2.83,
            2.89,
            3.04,
            3.13,
            4.45,
            5.97,
            6.03,
            6.16,
            6.18,
            6.47,
            6.72,
            6.76,
            6.84,
            7.12,
            7.51,
            7.6,
            9.59,
            9.6,
            9.69,
            9.7,
            9.78,
            9.96,
            10.04,
            10.65,
            10.86,
            10.97,
            12.44,
            12.56,
            12.71,
            12.8,
            12.88,
            12.89,
            13.21,
            32.03,
            32.32,
            32.37,
            32.44,
            32.95,
            33.07,
            33.08,
            33.16,
            33.27,
            33.31,
            33.51,
            33.66,
            34.32,
            34.63,
            34.79,
            34.82,
            35.28,
            35.77,
            36.83,
            45.03,
            45.99,
            76.21,
            76.31,
            79.76,
            95.38,
            99.17,
            99.23,
            99.34,
            99.35,
            99.37,
            100.03,
            100.04,
            100.11,
            100.54,
            100.65,
            100.83,
            101.03,
            101.05,
            101.83,
            102.06,
            102.71,
            103.04,
            103.12,
            103.36,
            103.44,
            104.2,
            104.33,
            105.38,
            105.49,
            105.83,
            106.03,
            106.27,
            106.29,
            106.72,
            106.73,
            107.08,
            107.41,
            107.46,
            107.8,
            108.07,
            108.74,
            112.3,
            112.39,
            112.52,
            112.9,
            113.91,
            118.36,
            119.08,
            119.18,
            180.41,
            180.69,
            180.93,
            181.11,
            182.2,
            183.82,
            185.19,
            280.92,
            281.06,
            281.96,
            282.21,
            284.82,
            285.54,
            600
        ],
        "Solution Costs: ": [
            null,
            640.8,
            620.4,
            605.3,
            593.9,
            593.4,
            585.7,
            502.3,
            490.8,
            485.0,
            480.6,
            461.2,
            460.9,
            448.2,
            438.2,
            391.5,
            381.2,
            371.2,
            366.2,
            354.8,
            349.1,
            344.2,
            340.8,
            334.5,
            334.2,
            333.2,
            330.2,
            329.5,
            328.6,
            327.9,
            322.3,
            319.3,
            318.7,
            315.8,
            315.1,
            310.5,
            304.3,
            301.0,
            299.7,
            298.2,
            297.8,
            291.4,
            291.3,
            291.3,
            289.8,
            288.7,
            287.8,
            287.2,
            286.5,
            285.3,
            283.7,
            283.6,
            283.5,
            281.5,
            280.2,
            278.7,
            278.6,
            271.9,
            271.8,
            270.6,
            269.5,
            268.8,
            267.4,
            266.8,
            266.2,
            262.9,
            262.5,
            262.1,
            262.0,
            261.4,
            260.2,
            259.9,
            259.6,
            259.2,
            258.9,
            256.4,
            254.7,
            254.4,
            252.9,
            248.8,
            248.5,
            247.5,
            246.8,
            246.5,
            246.3,
            246.1,
            246.0,
            244.8,
            244.3,
            243.6,
            241.7,
            241.5,
            241.4,
            241.0,
            240.9,
            239.0,
            238.8,
            236.9,
            236.5,
            235.5,
            235.5,
            233.4,
            232.0,
            230.4,
            229.7,
            229.3,
            229.1,
            228.6,
            227.8,
            227.6,
            227.6,
            227.5,
            226.9,
            226.0,
            225.9,
            225.9,
            224.7,
            223.1,
            222.4,
            221.7,
            221.5,
            221.4,
            220.7,
            220.4,
            220.2,
            220.0,
            217.3,
            215.3,
            214.7,
            214.3,
            214.0,
            213.8,
            213.6,
            213.2,
            212.1,
            211.9,
            211.7,
            211.7,
            211.7,
            210.5,
            210.4,
            210.1,
            210.0,
            209.7,
            209.5,
            209.4,
            209.3,
            209.2,
            208.9,
            208.9,
            208.5,
            208.5,
            208.5,
            208.5
        ],
        "Optimality: ": false,
        "Best Cost: ": 208.5,
        "Best Path: ": [
            [
                40,
                20,
                26,
                39,
                8,
                47
            ],
            [
                14,
                2,
                46,
                18
            ],
            [
                28,
                29,
                13,
                30,
                21,
                33,
                10,
                41
            ],
            [
                16,
                24,
                4,
                11,
                42,
                15,
                27
            ],
            [
                23,
                5,
                22,
                25,
                3,
                37,
                44
            ],
            [
                12,
                36,
                7,
                45,
                9,
                34,
                17
            ],
            [
                35,
                1,
                6,
                31,
                43,
                32,
                19,
                38
            ]
        ]
    },
    "CP_Model_GTR": {
        "Times: ": [
            0,
            0.48,
            0.5,
            0.5,
            0.5,
            0.5,
            0.51,
            0.51,
            0.51,
            0.52,
            0.52,
            0.53,
            0.54,
            0.54,
            0.55,
            0.55,
            0.55,
            0.55,
            0.55,
            0.55,
            0.56,
            0.56,
            0.56,
            0.57,
            0.57,
            0.59,
            0.61,
            0.62,
            0.62,
            0.62,
            0.63,
            0.65,
            0.73,
            0.75,
            0.76,
            0.82,
            0.83,
            0.84,
            0.85,
            0.85,
            0.87,
            0.87,
            0.89,
            0.9,
            0.93,
            0.94,
            0.94,
            0.94,
            0.96,
            0.96,
            0.97,
            0.97,
            0.98,
            0.99,
            1.01,
            1.05,
            1.08,
            1.09,
            1.09,
            1.13,
            1.23,
            1.23,
            1.24,
            1.26,
            1.26,
            1.26,
            1.35,
            1.36,
            1.42,
            1.44,
            1.49,
            1.49,
            1.51,
            1.54,
            1.58,
            1.62,
            1.62,
            1.68,
            1.68,
            1.71,
            1.74,
            1.75,
            2.72,
            2.74,
            2.76,
            2.76,
            2.77,
            2.78,
            2.8,
            2.86,
            2.95,
            2.96,
            2.96,
            2.96,
            2.98,
            3.02,
            3.04,
            3.05,
            3.13,
            3.14,
            3.17,
            3.29,
            3.36,
            3.52,
            3.52,
            3.56,
            3.57,
            3.59,
            3.59,
            3.63,
            3.64,
            3.66,
            3.69,
            3.71,
            3.73,
            3.75,
            3.82,
            3.82,
            3.84,
            4.0,
            4.01,
            4.11,
            4.54,
            4.58,
            4.6,
            5.35,
            5.4,
            5.56,
            5.56,
            7.12,
            7.13,
            7.51,
            7.55,
            7.56,
            8.96,
            8.97,
            9.58,
            9.59,
            9.75,
            9.87,
            10.62,
            11.02,
            11.06,
            17.86,
            17.89,
            18.0,
            82.89,
            83.36,
            88.19,
            91.22,
            91.41,
            91.42,
            91.42,
            600
        ],
        "Solution Costs: ": [
            null,
            584.9,
            548.9,
            473.2,
            472.1,
            447.5,
            428.5,
            420.5,
            403.2,
            387.6,
            372.0,
            370.5,
            369.5,
            365.6,
            365.5,
            357.0,
            352.8,
            343.1,
            340.3,
            340.2,
            338.0,
            336.1,
            333.4,
            327.3,
            325.2,
            323.2,
            315.2,
            313.1,
            312.6,
            307.0,
            306.8,
            305.9,
            305.2,
            304.3,
            303.5,
            302.8,
            302.3,
            300.4,
            296.4,
            293.3,
            292.9,
            286.3,
            285.8,
            284.7,
            282.6,
            277.1,
            277.0,
            276.8,
            274.6,
            271.1,
            270.9,
            270.9,
            270.2,
            264.5,
            264.0,
            264.0,
            263.5,
            260.8,
            259.9,
            256.9,
            255.0,
            254.1,
            251.4,
            250.3,
            249.9,
            248.1,
            248.1,
            248.1,
            247.6,
            246.6,
            245.2,
            244.0,
            243.0,
            242.0,
            239.9,
            239.4,
            237.7,
            236.7,
            236.3,
            235.9,
            233.7,
            232.6,
            232.4,
            232.1,
            232.0,
            230.2,
            230.2,
            229.9,
            228.7,
            227.1,
            226.7,
            225.3,
            225.1,
            224.8,
            224.1,
            223.9,
            223.2,
            223.0,
            222.3,
            221.5,
            221.0,
            220.6,
            220.4,
            219.2,
            218.8,
            217.3,
            217.3,
            216.3,
            216.2,
            215.3,
            215.0,
            214.4,
            213.4,
            213.2,
            213.0,
            213.0,
            212.8,
            211.7,
            211.5,
            210.8,
            210.2,
            209.0,
            208.9,
            208.6,
            208.1,
            208.1,
            207.2,
            207.0,
            207.0,
            206.9,
            206.7,
            206.4,
            205.9,
            205.8,
            203.7,
            203.7,
            203.4,
            203.3,
            203.0,
            202.7,
            202.6,
            202.5,
            202.5,
            201.6,
            201.5,
            201.5,
            201.3,
            201.0,
            200.9,
            199.4,
            198.7,
            198.6,
            198.4
        ],
        "Optimality: ": false,
        "Best Cost: ": 198.4,
        "Best Path: ": [
            [
                41,
                2,
                10,
                29,
                33,
                16
            ],
            [
                28,
                13,
                46,
                30,
                21,
                47,
                17
            ],
            [
                40,
                45,
                8,
                3,
                37,
                36
            ],
            [
                27,
                15,
                39,
                26,
                20,
                7,
                18
            ],
            [
                35,
                32,
                19,
                38,
                31,
                12,
                43,
                23,
                14
            ],
            [
                44,
                22,
                25,
                1,
                6,
                5
            ],
            [
                24,
                4,
                11,
                42,
                9,
                34
            ]
        ]
    },
    "DIDP_GTR_Complete": {
        "Times: ": [
            0,
            0.0018682,
            0.002832,
            0.0041025,
            0.0059395,
            0.0146266,
            0.0211448,
            0.0216661,
            0.0302816,
            0.0311693,
            0.0369113,
            0.0492594,
            0.0508222,
            0.1176781,
            0.4035948,
            7.6606148,
            7.893306,
            7.9783101,
            7.9854078,
            8.1384056,
            8.1393711,
            8.1433216,
            8.1723978,
            8.2317996,
            11.0404491,
            11.0427508,
            11.0749016,
            11.1717106,
            11.1748353,
            15.7387475,
            30.000862,
            30.7571619,
            31.0099965,
            31.0105575,
            31.0114503,
            31.1262354,
            31.1478373,
            31.1797617,
            31.3970722,
            31.8204208,
            62.7959083,
            62.899412,
            468.8773857,
            591.6956273,
            591.7254468,
            591.7773376,
            591.7904656,
            591.798973,
            591.8426434,
            591.8436211,
            591.8680038,
            591.9967891,
            600.4908706,
            600
        ],
        "Solution Costs: ": [
            null,
            339.5,
            332.7,
            330.5,
            330.1,
            307.7,
            307.5,
            295.7,
            280.9,
            270.1,
            268.9,
            266.6,
            265.3,
            259.6,
            257.3,
            255.6,
            255.6,
            252.7,
            252.6,
            252.5,
            252.5,
            251.9,
            251.3,
            250.5,
            244.0,
            243.3,
            239.6,
            238.3,
            237.5,
            237.5,
            236.6,
            236.6,
            236.4,
            235.3,
            233.7,
            231.1,
            231.0,
            226.1,
            222.3,
            222.0,
            221.8,
            221.5,
            219.7,
            219.6,
            219.3,
            218.6,
            217.4,
            216.6,
            214.4,
            212.5,
            212.3,
            210.6,
            210.6
        ],
        "Optimality: ": false,
        "Best Cost: ": 210.6,
        "Best Path: ": [
            [
                24,
                4,
                13,
                46,
                30,
                21,
                33
            ],
            [
                45,
                9,
                42,
                11,
                29,
                47
            ],
            [
                15,
                20,
                26,
                39,
                8,
                27
            ],
            [
                19,
                25,
                38,
                37,
                3,
                7,
                36
            ],
            [
                34,
                28,
                10,
                2,
                16,
                40,
                17
            ],
            [
                14,
                22,
                1,
                6,
                5,
                23
            ],
            [
                41,
                31,
                12,
                43,
                32,
                35,
                44,
                18
            ]
        ]
    },
    "DIDP_GTR_No_Bound": {
        "Times: ": [
            0,
            0.0035115,
            0.0024889,
            0.0330517,
            0.0586474,
            0.0603274,
            0.1029678,
            0.1066461,
            0.1088087,
            0.1283277,
            0.1335534,
            0.1459892,
            0.1500287,
            0.1551346,
            0.1720368,
            0.2167353,
            0.376882,
            0.4027788,
            0.8763911,
            1.0819599,
            1.1095285,
            1.30496,
            1.5575314,
            1.5593249,
            1.5640132,
            1.5684114999999998,
            1.5706824,
            2.4140398,
            2.4142009,
            2.7128005,
            36.3468493,
            36.3506086,
            36.3625962,
            36.4180321,
            36.5090939,
            38.1875596,
            154.1714414,
            154.1727346,
            154.2271078,
            165.298976,
            170.687873,
            170.6894448,
            170.6961861,
            170.7014525,
            170.8631631,
            170.8689205,
            170.9922152,
            289.6933822,
            290.0355214,
            600.2918849,
            600
        ],
        "Solution Costs: ": [
            null,
            475.3,
            469.8,
            462.9,
            419.9,
            413.9,
            380.0,
            376.7,
            371.6,
            361.8,
            356.4,
            354.1,
            349.6,
            327.4,
            322.6,
            313.5,
            311.5,
            302.6,
            297.0,
            295.2,
            292.7,
            286.8,
            268.6,
            267.8,
            266.0,
            262.5,
            262.3,
            260.3,
            248.5,
            242.6,
            241.4,
            239.8,
            238.4,
            237.9,
            236.6,
            235.6,
            234.0,
            233.7,
            233.1,
            232.5,
            232.2,
            231.9,
            231.4,
            229.7,
            229.0,
            228.4,
            227.0,
            224.7,
            224.1,
            224.1
        ],
        "Optimality: ": false,
        "Best Cost: ": 224.1,
        "Best Path: ": [
            [
                18,
                44,
                35,
                23,
                43,
                31,
                1,
                22,
                32
            ],
            [
                29,
                4,
                11,
                13,
                30,
                33
            ],
            [
                14,
                45,
                34,
                15,
                39,
                20,
                3,
                7
            ],
            [
                19,
                37,
                6,
                12
            ],
            [
                17,
                40,
                38,
                25,
                36,
                5
            ],
            [
                16,
                28,
                9,
                24,
                42,
                26,
                8,
                27
            ],
            [
                41,
                2,
                10,
                46,
                21,
                47
            ]
        ]
    },
    "DIDP_GTR_No_Implied": {
        "Times: ": [
            0,
            0.001592,
            0.0022825,
            0.0042364,
            0.0085639,
            0.0110405,
            0.0190691,
            0.0330535,
            0.0384057,
            0.041035,
            0.0502187,
            0.0618669,
            0.0648527,
            0.0933709,
            0.1015623,
            0.1057019,
            0.1201846,
            0.1260825,
            0.2513835,
            0.2548662,
            0.3106748,
            0.3238787,
            0.3364404,
            0.3411797,
            0.3422689,
            0.3427203,
            0.3565476,
            1.8505549000000001,
            3.0489806,
            3.0510879,
            3.0563849,
            3.0675822,
            3.0708989,
            3.0725906,
            3.112052,
            4.9139206,
            4.9177988,
            4.919059,
            4.9267397,
            4.9380838,
            4.9448504,
            5.5006329,
            5.5299618,
            5.6106887,
            8.4902392,
            8.9317874,
            9.167961,
            70.6172314,
            70.6320262,
            71.4801991,
            221.201971,
            221.2513099,
            221.2525117,
            221.2812753,
            221.2852989,
            221.3103701,
            221.3138264,
            221.3145147,
            221.6279378,
            221.6290356,
            221.6340501,
            221.8505226,
            221.8762341,
            221.8892544,
            222.2177946,
            223.9248328,
            223.9359226,
            224.1031243,
            323.7426027,
            323.8141269,
            323.8555666,
            323.91019,
            324.0097497,
            324.3622438,
            324.3771987,
            324.642517,
            325.8709086,
            325.9911699,
            327.6277152,
            600.6348726,
            600
        ],
        "Solution Costs: ": [
            null,
            339.5,
            332.7,
            315.4,
            314.6,
            300.8,
            300.8,
            295.8,
            295.2,
            295.1,
            294.5,
            292.7,
            281.1,
            277.6,
            275.9,
            272.4,
            268.9,
            267.9,
            266.8,
            266.7,
            264.5,
            262.5,
            259.7,
            259.3,
            255.9,
            254.4,
            248.8,
            247.1,
            243.8,
            242.6,
            241.5,
            240.5,
            239.4,
            239.0,
            237.9,
            236.6,
            233.4,
            231.9,
            230.6,
            229.6,
            229.5,
            228.5,
            227.7,
            226.8,
            226.8,
            225.7,
            224.8,
            223.7,
            221.4,
            220.7,
            218.4,
            218.1,
            217.0,
            216.6,
            216.1,
            214.4,
            214.2,
            213.2,
            212.8,
            212.2,
            212.0,
            211.3,
            211.3,
            211.2,
            210.6,
            209.6,
            209.3,
            208.5,
            208.3,
            208.1,
            207.6,
            207.5,
            206.4,
            204.9,
            203.5,
            203.1,
            202.7,
            201.9,
            201.7,
            201.7
        ],
        "Optimality: ": false,
        "Best Cost: ": 201.7,
        "Best Path: ": [
            [
                39,
                26,
                20,
                8,
                15,
                45
            ],
            [
                9,
                42,
                11,
                4,
                24,
                29
            ],
            [
                21,
                30,
                13,
                46,
                33,
                16
            ],
            [
                27,
                34,
                28,
                10,
                2,
                47,
                17
            ],
            [
                40,
                3,
                25,
                19,
                38,
                37,
                18
            ],
            [
                7,
                22,
                1,
                6,
                32,
                36,
                35,
                44
            ],
            [
                31,
                5,
                12,
                43,
                23,
                14,
                41
            ]
        ]
    },
    "DIDP_GTR_Base": {
        "Times: ": [
            0,
            0.0031256,
            0.002413,
            0.0244927,
            0.0248843,
            0.0478239,
            0.0490984,
            0.2106977,
            0.2181227,
            0.2229559,
            0.2308859,
            0.2340931,
            0.2490448,
            0.2559153,
            0.2802722,
            0.3440706,
            0.3571795,
            0.4751393,
            0.4942958,
            0.5116557,
            0.5339608,
            0.5461668,
            0.5992029,
            0.6238929,
            1.4981078,
            1.6656933,
            2.0399561,
            2.0454297,
            2.4682166,
            5.5459378,
            8.6413568,
            36.2757802,
            75.1724129,
            521.7633655,
            522.3512364,
            527.8595215,
            531.0918479,
            600.2629781,
            600
        ],
        "Solution Costs: ": [
            null,
            475.3,
            469.8,
            454.4,
            449.7,
            427.4,
            418.8,
            415.9,
            406.0,
            388.9,
            387.1,
            378.1,
            372.9,
            369.1,
            367.8,
            367.0,
            366.0,
            339.8,
            335.7,
            321.8,
            304.8,
            295.2,
            294.0,
            292.3,
            286.8,
            279.9,
            279.6,
            277.6,
            269.3,
            258.9,
            246.7,
            244.7,
            244.7,
            244.2,
            240.3,
            239.7,
            239.5,
            239.5
        ],
        "Optimality: ": false,
        "Best Cost: ": 239.5,
        "Best Path: ": [
            [
                14,
                17,
                18,
                44
            ],
            [
                12,
                5,
                31,
                43,
                23
            ],
            [
                35,
                40,
                7,
                45,
                34,
                9,
                24,
                13,
                30,
                21,
                29,
                28
            ],
            [
                22,
                38,
                37,
                16,
                10,
                41
            ],
            [
                1,
                6,
                25,
                19,
                3,
                8
            ],
            [
                2,
                33,
                46,
                4,
                42,
                15,
                27
            ],
            [
                47,
                11,
                20,
                26,
                39,
                36,
                32
            ]
        ]
    }
}